odoo10_addon_crm_sector-10.0.1.0.0-py2.7-nspkg.pth
odoo/addons/crm_sector/README.rst
odoo/addons/crm_sector/__init__.py
odoo/addons/crm_sector/__manifest__.py
odoo/addons/crm_sector/i18n/bg.po
odoo/addons/crm_sector/i18n/de.po
odoo/addons/crm_sector/i18n/es.po
odoo/addons/crm_sector/i18n/fr.po
odoo/addons/crm_sector/i18n/hr.po
odoo/addons/crm_sector/i18n/it.po
odoo/addons/crm_sector/i18n/nb.po
odoo/addons/crm_sector/i18n/pt_BR.po
odoo/addons/crm_sector/i18n/sk.po
odoo/addons/crm_sector/i18n/sl.po
odoo/addons/crm_sector/i18n/sv.po
odoo/addons/crm_sector/i18n/tr.po
odoo/addons/crm_sector/i18n/tr_TR.po
odoo/addons/crm_sector/i18n/zh_CN.po
odoo/addons/crm_sector/models/__init__.py
odoo/addons/crm_sector/models/crm_lead.py
odoo/addons/crm_sector/static/description/icon.png
odoo/addons/crm_sector/tests/__init__.py
odoo/addons/crm_sector/tests/test_crm_lead.py
odoo/addons/crm_sector/views/crm_lead_view.xml
odoo10_addon_crm_sector-10.0.1.0.0.dist-info/DESCRIPTION.rst
odoo10_addon_crm_sector-10.0.1.0.0.dist-info/METADATA
odoo10_addon_crm_sector-10.0.1.0.0.dist-info/RECORD
odoo10_addon_crm_sector-10.0.1.0.0.dist-info/WHEEL
odoo10_addon_crm_sector-10.0.1.0.0.dist-info/metadata.json
odoo10_addon_crm_sector-10.0.1.0.0.dist-info/namespace_packages.txt
odoo10_addon_crm_sector-10.0.1.0.0.dist-info/top_level.txt
